{
  "0": [],
  "1": [
    {
      "name": "Financial Econometrics and Modelling",
      "tutor": "Omon Ganiev",
      "type": "seminar",
      "start": 11.0,
      "length": 2.0,
      "location": "IB302"
    },
    {
      "name": "Corporate Governance for Finance",
      "tutor": "Hasan AKM Kamrul",
      "type": "lecture",
      "start": 13.0,
      "length": 1.0,
      "location": "SHB206 H"
    }
  ],
  "2": [],
  "3": [
    {
      "name": "Management Accounting",
      "tutor": "Feruza Yodgorova",
      "type": "online lecture",
      "start": 12.0,
      "length": 1.0,
      "location": "IB311"
    },
    {
      "name": "Management Accounting",
      "tutor": "Abdul Aziz Buriev",
      "type": "seminar",
      "start": 15.0,
      "length": 2.0,
      "location": "IB216"
    },
    {
      "name": "Management Accounting",
      "tutor": "Abdul Aziz Buriev",
      "type": "workshop",
      "start": 17.0,
      "length": 1.0,
      "location": "IB208 CL"
    }
  ],
  "4": [
    {
      "name": "Financial Econometrics and Modelling",
      "tutor": "Omon Ganiev",
      "type": "workshop",
      "start": 12.0,
      "length": 2.0,
      "location": "IB209 CL"
    }
  ],
  "5": [
    {
      "name": "Corporate Governance for Finance",
      "tutor": "Hasan AKM Kamrul",
      "type": "seminar",
      "start": 9.0,
      "length": 2.0,
      "location": "ATB307"
    },
    {
      "name": "Corporate Governance for Finance",
      "tutor": "Hasan AKM Kamrul",
      "type": "workshop",
      "start": 11.0,
      "length": 1.0,
      "location": "ATB307"
    }
  ],
  "6": [],
  "7": []
}