{
  "0": [],
  "1": [
    {
      "name": "Foundations of Economics",
      "tutor": "Gulnoza Kuldosheva",
      "type": "seminar",
      "start": 12.0,
      "length": 2.0,
      "location": "ATB307"
    },
    {
      "name": "Academic English",
      "tutor": "Temur Saidnazarov",
      "type": "seminar",
      "start": 14.0,
      "length": 2.0,
      "location": "New207"
    }
  ],
  "2": [
    {
      "name": "Business in the Modern World",
      "tutor": "Sanemkhan Nurillaeva",
      "type": "lecture",
      "start": 10.0,
      "length": 1.0,
      "location": "Lyceum hall"
    },
    {
      "name": "Foundations of Economics",
      "tutor": "Jamshid Normatov",
      "type": "lecture",
      "start": 12.0,
      "length": 2.0,
      "location": "IB301"
    }
  ],
  "3": [
    {
      "name": "I, Citizen",
      "tutor": "Ma'ruf Karimov",
      "type": "seminar",
      "start": 12.0,
      "length": 2.0,
      "location": "Lyceum 91"
    }
  ],
  "4": [
    {
      "name": "Academic English",
      "tutor": "Temur Saidnazarov",
      "type": "seminar",
      "start": 14.0,
      "length": 2.0,
      "location": "New301"
    },
    {
      "name": "Business in the Modern World",
      "tutor": "Nadezhda Kim",
      "type": "seminar",
      "start": 16.0,
      "length": 2.0,
      "location": "Lyceum 96"
    }
  ],
  "5": [
    {
      "name": "Developing Professional Identity",
      "tutor": "Nodira Isamukhamedova",
      "type": "seminar",
      "start": 12.0,
      "length": 2.0,
      "location": "Lyceum 93"
    }
  ],
  "6": [],
  "7": []
}
